<?xml version="1.0" encoding="utf-8"?>
<LanguageData>
    <FamilyPerson_NearChildren.stages.0.label>Радость рядом с ребёнком</FamilyPerson_NearChildren.stages.0.label>
    <FamilyPerson_NearChildren.stages.0.description>Чувствую радость, находясь рядом с малышом.</FamilyPerson_NearChildren.stages.0.description>

    <FamilyPerson_NearChildren.stages.1.label>Радость рядом с детьми</FamilyPerson_NearChildren.stages.1.label>
    <FamilyPerson_NearChildren.stages.1.description>Рядом с малышами я чувствую счастье!</FamilyPerson_NearChildren.stages.1.description>
</LanguageData>

